cvcuda/__init__.py
cvcuda/_cvcuda.cpython-310-x86_64-linux-gnu.so
cvcuda/_cvcuda.cpython-311-x86_64-linux-gnu.so
cvcuda/_cvcuda.cpython-312-x86_64-linux-gnu.so
cvcuda/_cvcuda.cpython-313-x86_64-linux-gnu.so
cvcuda/_cvcuda.cpython-314-x86_64-linux-gnu.so
cvcuda/_cvcuda.cpython-39-x86_64-linux-gnu.so
cvcuda_cu13.libs/libcvcuda-07ee5812.so.0.16.0
cvcuda_cu13.libs/libnvcv_types-4a87ea36.so.0.16.0
cvcuda_cu13-0.16.0.dist-info/METADATA
cvcuda_cu13-0.16.0.dist-info/WHEEL
cvcuda_cu13-0.16.0.dist-info/top_level.txt
cvcuda_cu13-0.16.0.dist-info/RECORD
