Metadata-Version: 2.4
Name: cvcuda-cu13
Version: 0.16.0
Summary: CUDA-accelerated Computer Vision algorithms
Home-page: https://cvcuda.github.io
Author: NVIDIA Corporation
Author-email: NVIDIA Corporation <support@nvidia.com>
Maintainer-email: NVIDIA Corporation <support@nvidia.com>
License: Apache-2.0
Project-URL: Homepage, https://cvcuda.github.io
Project-URL: Documentation, https://cvcuda.github.io
Project-URL: Repository, https://github.com/CVCUDA/CV-CUDA
Project-URL: Bug Tracker, https://github.com/CVCUDA/CV-CUDA/issues
Project-URL: Changelog, https://github.com/CVCUDA/CV-CUDA/releases
Keywords: cuda,computer-vision,image-processing,nvidia,gpu
Classifier: Development Status :: 4 - Beta
Classifier: Environment :: GPU :: NVIDIA CUDA
Classifier: Environment :: GPU :: NVIDIA CUDA :: 13
Classifier: Intended Audience :: Developers
Classifier: Intended Audience :: Science/Research
Classifier: License :: OSI Approved :: Apache Software License
Classifier: Operating System :: POSIX :: Linux
Classifier: Programming Language :: C++
Classifier: Programming Language :: Python :: 3
Classifier: Programming Language :: Python :: 3.9
Classifier: Programming Language :: Python :: 3.10
Classifier: Programming Language :: Python :: 3.11
Classifier: Programming Language :: Python :: 3.12
Classifier: Programming Language :: Python :: 3.13
Classifier: Programming Language :: Python :: 3.14
Classifier: Programming Language :: Python :: Implementation :: CPython
Classifier: Topic :: Scientific/Engineering
Classifier: Topic :: Scientific/Engineering :: Artificial Intelligence
Classifier: Topic :: Scientific/Engineering :: Image Processing
Classifier: Topic :: Software Development :: Libraries
Requires-Python: >=3.9, <3.15
Requires-Dist: numpy>=1.23.5
Provides-Extra: dev
Requires-Dist: pytest>=7.0; extra == "dev"
Requires-Dist: black>=22.0; extra == "dev"
Requires-Dist: flake8>=4.0; extra == "dev"
Dynamic: author
Dynamic: home-page
Dynamic: requires-python
